muaythai_combo/__init__.py
muaythai_combo/app.py
muaythai_combo-0.1.2.dist-info/METADATA
muaythai_combo-0.1.2.dist-info/WHEEL
muaythai_combo-0.1.2.dist-info/entry_points.txt
muaythai_combo-0.1.2.dist-info/top_level.txt
muaythai_combo-0.1.2.dist-info/RECORD
