Metadata-Version: 2.1
Name: muaythai_combo
Version: 0.1.2
Summary: Muay Thai Combo Generator with Tkinter
Author: Sam Porter
Author-email: sam.porter.18@ucl.ac.uk
Classifier: Programming Language :: Python :: 3
Classifier: Operating System :: OS Independent
Requires-Python: >=3.6
